dash_stylish_header/__init__.py
dash_stylish_header/header.py
dash_stylish_header-0.0.1.dist-info/METADATA
dash_stylish_header-0.0.1.dist-info/WHEEL
dash_stylish_header-0.0.1.dist-info/entry_points.txt
dash_stylish_header-0.0.1.dist-info/top_level.txt
dash_stylish_header-0.0.1.dist-info/RECORD
