Metadata-Version: 2.4
Name: dash_stylish_header
Version: 0.0.1
Summary: Stylish header component for Dash applications using Dash Hooks
Author-email: Plotly <info@plotly.com>
Requires-Python: >=3.7
Requires-Dist: dash>=3.0.0
Provides-Extra: dev
Requires-Dist: pytest>=6.0; extra == "dev"
Requires-Dist: ruff>=0.11.0; extra == "dev"
